Workbook
Name QBCANSUPPORTUPDATE: TRUE
Name QBCOMPANYFILENAME: "C:\Users\17782\Desktop\$$Data Files\$QuickBooks Files\$Russell Mcmann Companies QB\McMann Group Inc\McMann Group Inc.QBW"
Name QBHEADERSONSCREEN: FALSE
Name QBMETADATASIZE: 8049
Name QBPRESERVECOLOR: TRUE
Name QBPRESERVEFONT: TRUE
Name QBPRESERVEROWHEIGHT: TRUE
Name QBPRESERVESPACE: TRUE
Name QBREPORTCOLAXIS: 0
Name QBREPORTCOMPANYID: "cdb3831d65524c189c285e069069d325"
Name QBREPORTCOMPARECOL_ANNUALBUDGET: FALSE
Name QBREPORTCOMPARECOL_AVGCOGS: FALSE
Name QBREPORTCOMPARECOL_AVGPRICE: FALSE
Name QBREPORTCOMPARECOL_BUDDIFF: FALSE
Name QBREPORTCOMPARECOL_BUDGET: FALSE
Name QBREPORTCOMPARECOL_BUDPCT: FALSE
Name QBREPORTCOMPARECOL_COGS: FALSE
Name QBREPORTCOMPARECOL_EXCLUDEAMOUNT: FALSE
Name QBREPORTCOMPARECOL_EXCLUDECURPERIOD: FALSE
Name QBREPORTCOMPARECOL_FORECAST: FALSE
Name QBREPORTCOMPARECOL_GROSSMARGIN: FALSE
Name QBREPORTCOMPARECOL_GROSSMARGINPCT: FALSE
Name QBREPORTCOMPARECOL_HOURS: FALSE
Name QBREPORTCOMPARECOL_PCTCOL: FALSE
Name QBREPORTCOMPARECOL_PCTEXPENSE: FALSE
Name QBREPORTCOMPARECOL_PCTINCOME: FALSE
Name QBREPORTCOMPARECOL_PCTOFSALES: FALSE
Name QBREPORTCOMPARECOL_PCTROW: FALSE
Name QBREPORTCOMPARECOL_PPDIFF: FALSE
Name QBREPORTCOMPARECOL_PPPCT: FALSE
Name QBREPORTCOMPARECOL_PREVPERIOD: FALSE
Name QBREPORTCOMPARECOL_PREVYEAR: FALSE
Name QBREPORTCOMPARECOL_PYDIFF: FALSE
Name QBREPORTCOMPARECOL_PYPCT: FALSE
Name QBREPORTCOMPARECOL_QTY: FALSE
Name QBREPORTCOMPARECOL_RATE: FALSE
Name QBREPORTCOMPARECOL_TRIPBILLEDMILES: FALSE
Name QBREPORTCOMPARECOL_TRIPBILLINGAMOUNT: FALSE
Name QBREPORTCOMPARECOL_TRIPMILES: FALSE
Name QBREPORTCOMPARECOL_TRIPNOTBILLABLEMILES: FALSE
Name QBREPORTCOMPARECOL_TRIPTAXDEDUCTIBLEAMOUNT: FALSE
Name QBREPORTCOMPARECOL_TRIPUNBILLEDMILES: FALSE
Name QBREPORTCOMPARECOL_YTD: FALSE
Name QBREPORTCOMPARECOL_YTDBUDGET: FALSE
Name QBREPORTCOMPARECOL_YTDPCT: FALSE
Name QBREPORTROWAXIS: 15
Name QBREPORTSUBCOLAXIS: 0
Name QBREPORTTYPE: 109
Name QBROWHEADERS: 2

Sheet Cost Breakdown
A2: LINE ITEM | B2: BUDGET | C2: Prev. Invoiced | D2: CURRENT INVOICE | E2: TOTAL INVOICED | F2: TO BE COMPLETED | G2: OVER BUDGET | H2: CHANGE ORDERS
A4: DESIGN SERVICES
A5: Plan Desgin | B5: 17850 | D5: =SUMIF(Material!$E:$E,TRIM(A5),Material!$F:$F) -> 9246.3 | E5: =SUM(C5:D5) -> 9246.3 | F5: =IF(AND(B5>0,B5>E5),B5-E5,0) -> 8603.7 | G5: =IF(AND(B5>0,B5<E5),B5-E5,0) -> 0 | H5: =IF(AND(B5=0,B5<E5),E5-B5,0) -> 0
A6: Plan Printing & Photocopying | B6: 525 | D6: =SUMIF(Material!$E:$E,TRIM(A6),Material!$F:$F) -> 158.93 | E6: =SUM(C6:D6) -> 158.93 | F6: =IF(AND(B6>0,B6>E6),B6-E6,0) -> 366.07 | G6: =IF(AND(B6>0,B6<E6),B6-E6,0) -> 0 | H6: 0
A7: DESIGN SERVICES — Subtotal | B7: =SUM(B5:B6) -> 18375 | C7: =SUM(C5:C6) -> 0 | D7: =SUM(D5:D6) -> 9405.23 | E7: =SUM(E5:E6) -> 9405.23 | F7: =SUM(F5:F6) -> 8969.77 | G7: =SUM(G5:G6) -> 0 | H7: =SUM(H5:H6) -> 0
A9: PERMITS & HOME WARRANTY
A10: Building Permit Fees | B10: 10500 | D10: =SUMIF(Material!$E:$E,TRIM(A10),Material!$F:$F) -> 8216.35 | E10: =SUM(C10:D10) -> 8216.35 | F10: =IF(AND(B10>0,B10>E10),B10-E10,0) -> 2283.65 | G10: =IF(AND(B10>0,B10<E10),B10-E10,0) -> 0 | H10: =IF(AND(B10=0,B10<E10),E10-B10,0) -> 0
A11: Home Warranty Registration & Fees | B11: 2100 | D11: =SUMIF(Material!$E:$E,TRIM(A11),Material!$F:$F) -> 1250 | E11: =SUM(C11:D11) -> 1250 | F11: =IF(AND(B11>0,B11>E11),B11-E11,0) -> 850 | G11: =IF(AND(B11>0,B11<E11),B11-E11,0) -> 0 | H11: 0
A12: BC Housing Registration Fee | B12: 42 | D12: =SUMIF(Material!$E:$E,TRIM(A12),Material!$F:$F) -> 40 | E12: =SUM(C12:D12) -> 40 | F12: =IF(AND(B12>0,B12>E12),B12-E12,0) -> 2 | G12: =IF(AND(B12>0,B12<E12),B12-E12,0) -> 0 | H12: =IF(AND(B12=0,B12<E12),E12-B12,0) -> 0
A13: DCC Fees | B13: 10500 | D13: =SUMIF(Material!$E:$E,TRIM(A13),Material!$F:$F) -> 0 | E13: =SUM(C13:D13) -> 0 | F13: =IF(AND(B13>0,B13>E13),B13-E13,0) -> 10500 | G13: =IF(AND(B13>0,B13<E13),B13-E13,0) -> 0 | H13: 0
A14: PERMITS & HOME WARRANTY — Subtotal | B14: =SUM(B10:B13) -> 23142 | C14: =SUM(C10:C13) -> 0 | D14: =SUM(D10:D13) -> 9506.35 | E14: =SUM(E10:E13) -> 9506.35 | F14: =SUM(F10:F13) -> 13635.65 | G14: =SUM(G10:G13) -> 0 | H14: =SUM(H10:H13) -> 0
A16: ENGINEERING FEES
A17: Energy Advisor | B17: 1575 | D17: =SUMIF(Material!$E:$E,TRIM(A17),Material!$F:$F) -> 918.75 | E17: =SUM(C17:D17) -> 918.75 | F17: =IF(AND(B17>0,B17>E17),B17-E17,0) -> 656.25 | G17: =IF(AND(B17>0,B17<E17),B17-E17,0) -> 0 | H17: =IF(AND(B17=0,B17<E17),E17-B17,0) -> 0
A18: Land Survey | B18: 8400 | D18: =SUMIF(Material!$E:$E,TRIM(A18),Material!$F:$F) -> 8035.13 | E18: =SUM(C18:D18) -> 8035.13 | F18: =IF(AND(B18>0,B18>E18),B18-E18,0) -> 364.87 | G18: =IF(AND(B18>0,B18<E18),B18-E18,0) -> 0 | H18: =IF(AND(B18=0,B18<E18),E18-B18,0) -> 0
A19: Geotechnical Engineering | B19: 2100 | D19: =SUMIF(Material!$E:$E,TRIM(A19),Material!$F:$F) -> 883.68 | E19: =SUM(C19:D19) -> 883.68 | F19: =IF(AND(B19>0,B19>E19),B19-E19,0) -> 1216.32 | G19: =IF(AND(B19>0,B19<E19),B19-E19,0) -> 0 | H19: =IF(AND(B19=0,B19<E19),E19-B19,0) -> 0
A20: Structural Engineering | B20: 7350 | D20: =SUMIF(Material!$E:$E,TRIM(A20),Material!$F:$F) -> 7849.17 | E20: =SUM(C20:D20) -> 7849.17 | F20: =IF(AND(B20>0,B20>E20),B20-E20,0) -> 0 | G20: =IF(AND(B20>0,B20<E20),B20-E20,0) -> -499.17 | H20: =IF(AND(B20=0,B20<E20),E20-B20,0) -> 0
A21: ENGINEERING FEES — Subtotal | B21: =SUM(B17:B20) -> 19425 | C21: =SUM(C17:C20) -> 0 | D21: =SUM(D17:D20) -> 17686.73 | E21: =SUM(E17:E20) -> 17686.73 | F21: =SUM(F17:F20) -> 2237.44 | G21: =SUM(G17:G20) -> -499.17 | H21: =SUM(H17:H20) -> 0
A23: SITE WORK
A24: Backfill, Perimeter & Drain Material | B24: 21000 | D24: =SUMIF(Material!$E:$E,TRIM(A24),Material!$F:$F) -> 25071.19 | E24: =SUM(C24:D24) -> 25071.19 | F24: =IF(AND(B24>0,B24>E24),B24-E24,0) -> 0 | G24: =IF(AND(B24>0,B24<E24),B24-E24,0) -> -4071.19 | H24: =IF(AND(B24=0,B24<E24),E24-B24,0) -> 0
A25: Excavation, Backfill, Perimeter & Drain Labour | B25: 21000 | D25: =SUMIF(Material!$E:$E,TRIM(A25),Material!$F:$F) -> 59319.02 | E25: =SUM(C25:D25) -> 59319.02 | F25: =IF(AND(B25>0,B25>E25),B25-E25,0) -> 0 | G25: =IF(AND(B25>0,B25<E25),B25-E25,0) -> -38319.02 | H25: =IF(AND(B25=0,B25<E25),E25-B25,0) -> 0
A26: Septic | B26: 26250 | D26: =SUMIF(Material!$E:$E,TRIM(A26),Material!$F:$F) -> 1795.5 | E26: =SUM(C26:D26) -> 1795.5 | F26: =IF(AND(B26>0,B26>E26),B26-E26,0) -> 24454.5 | G26: =IF(AND(B26>0,B26<E26),B26-E26,0) -> 0 | H26: =IF(AND(B26=0,B26<E26),E26-B26,0) -> 0
A27: SITE WORK — Subtotal | B27: =SUM(B24:B26) -> 68250 | C27: =SUM(C24:C26) -> 0 | D27: =SUM(D24:D26) -> 86185.71 | E27: =SUM(E24:E26) -> 86185.71 | F27: =SUM(F24:F26) -> 24454.5 | G27: =SUM(G24:G26) -> -42390.21 | H27: =SUM(H24:H26) -> 0
A29: FOUNDATION
A30: Footings and Foundation Material | B30: 8597.5365 | D30: =SUMIF(Material!$E:$E,TRIM(A30),Material!$F:$F) -> 16250.66 | E30: =SUM(C30:D30) -> 16250.66 | F30: =IF(AND(B30>0,B30>E30),B30-E30,0) -> 0 | G30: =IF(AND(B30>0,B30<E30),B30-E30,0) -> -7653.1235 | H30: =IF(AND(B30=0,B30<E30),E30-B30,0) -> 0
A31: Foundation & Footings concrete | B31: 28140 | D31: =SUMIF(Material!$E:$E,TRIM(A31),Material!$F:$F) -> 23549.78 | E31: =SUM(C31:D31) -> 23549.78 | F31: =IF(AND(B31>0,B31>E31),B31-E31,0) -> 4590.22 | G31: =IF(AND(B31>0,B31<E31),B31-E31,0) -> 0 | H31: =IF(AND(B31=0,B31<E31),E31-B31,0) -> 0
A32: Footings & Foundation Labor | B32: 13649.38 | D32: =SUMIF(Material!$E:$E,TRIM(A32),Material!$F:$F) -> 15750 | E32: =SUM(C32:D32) -> 15750 | F32: =IF(AND(B32>0,B32>E32),B32-E32,0) -> 0 | G32: =IF(AND(B32>0,B32<E32),B32-E32,0) -> -2100.6195 | H32: =IF(AND(B32=0,B32<E32),E32-B32,0) -> 0
A33: Slab Prep - Material | B33: 435.372 | D33: =SUMIF(Material!$E:$E,TRIM(A33),Material!$F:$F) -> 0 | E33: =SUM(C33:D33) -> 0 | F33: =IF(AND(B33>0,B33>E33),B33-E33,0) -> 435.372 | G33: =IF(AND(B33>0,B33<E33),B33-E33,0) -> 0 | H33: =IF(AND(B33=0,B33<E33),E33-B33,0) -> 0
A34: Garage Concrete Slab | B34: 5040 | D34: =SUMIF(Material!$E:$E,TRIM(A34),Material!$F:$F) -> 4074.01 | E34: =SUM(C34:D34) -> 4074.01 | F34: =IF(AND(B34>0,B34>E34),B34-E34,0) -> 965.99 | G34: =IF(AND(B34>0,B34<E34),B34-E34,0) -> 0 | H34: =IF(AND(B34=0,B34<E34),E34-B34,0) -> 0
A35: Concrete Skim Coat Materials | B35: 6300 | D35: =SUMIF(Material!$E:$E,TRIM(A35),Material!$F:$F) -> 5354.94 | E35: =SUM(C35:D35) -> 5354.94 | F35: =IF(AND(B35>0,B35>E35),B35-E35,0) -> 945.06 | G35: =IF(AND(B35>0,B35<E35),B35-E35,0) -> 0 | H35: =IF(AND(B35=0,B35<E35),E35-B35,0) -> 0
A36: Garage Concrete Slab Finishing Labor | B36: 3620.925 | D36: =SUMIF(Material!$E:$E,TRIM(A36),Material!$F:$F) -> 0 | E36: =SUM(C36:D36) -> 0 | F36: =IF(AND(B36>0,B36>E36),B36-E36,0) -> 3620.925 | G36: =IF(AND(B36>0,B36<E36),B36-E36,0) -> 0 | H36: =IF(AND(B36=0,B36<E36),E36-B36,0) -> 0
A37: Concrete Pump Truck | B37: 3780 | D37: =SUMIF(Material!$E:$E,TRIM(A37),Material!$F:$F) -> 3664.42 | E37: =SUM(C37:D37) -> 3664.42 | F37: =IF(AND(B37>0,B37>E37),B37-E37,0) -> 115.58 | G37: =IF(AND(B37>0,B37<E37),B37-E37,0) -> 0 | H37: =IF(AND(B37=0,B37<E37),E37-B37,0) -> 0
A38: Damproofing | B38: 10500 | D38: =SUMIF(Material!$E:$E,TRIM(A38),Material!$F:$F) -> 3379.95 | E38: =SUM(C38:D38) -> 3379.95 | F38: =IF(AND(B38>0,B38>E38),B38-E38,0) -> 7120.05 | G38: =IF(AND(B38>0,B38<E38),B38-E38,0) -> 0 | H38: =IF(AND(B38=0,B38<E38),E38-B38,0) -> 0
A39: FOUNDATION — Subtotal | B39: =SUM(B30:B38) -> 80063.214 | C39: =SUM(C30:C38) -> 0 | D39: =SUM(D30:D38) -> 72023.76 | E39: =SUM(E30:E38) -> 72023.76 | F39: =SUM(F30:F38) -> 17793.197 | G39: =SUM(G30:G38) -> -9753.743 | H39: =SUM(H30:H38) -> 0
A41: FRAMING
A42: Framing Materials Cost | B42: 41235.086 | D42: =SUMIF(Material!$E:$E,TRIM(A42),Material!$F:$F) -> 59647.01 | E42: =SUM(C42:D42) -> 59647.01 | F42: =IF(AND(B42>0,B42>E42),B42-E42,0) -> 0 | G42: =IF(AND(B42>0,B42<E42),B42-E42,0) -> -18411.925 | H42: =IF(AND(B42=0,B42<E42),E42-B42,0) -> 0
A43: Roof Trusses | B43: 45150 | D43: =SUMIF(Material!$E:$E,TRIM(A43),Material!$F:$F) -> 43603.7 | E43: =SUM(C43:D43) -> 43603.7 | F43: =IF(AND(B43>0,B43>E43),B43-E43,0) -> 1546.3 | G43: =IF(AND(B43>0,B43<E43),B43-E43,0) -> 0 | H43: =IF(AND(B43=0,B43<E43),E43-B43,0) -> 0
A44: Floor System | B44: 14275.684 | D44: =SUMIF(Material!$E:$E,TRIM(A44),Material!$F:$F) -> 12383 | E44: =SUM(C44:D44) -> 12383 | F44: =IF(AND(B44>0,B44>E44),B44-E44,0) -> 1892.6845 | G44: =IF(AND(B44>0,B44<E44),B44-E44,0) -> 0 | H44: =IF(AND(B44=0,B44<E44),E44-B44,0) -> 0
A45: Engineering Hardware | B45: 11718.22 | D45: =SUMIF(Material!$E:$E,TRIM(A45),Material!$F:$F) -> 0 | E45: =SUM(C45:D45) -> 0 | F45: =IF(AND(B45>0,B45>E45),B45-E45,0) -> 11718.22 | G45: =IF(AND(B45>0,B45<E45),B45-E45,0) -> 0 | H45: =IF(AND(B45=0,B45<E45),E45-B45,0) -> 0
A46: Extra | B46: 5250 | D46: =SUMIF(Material!$E:$E,TRIM(A46),Material!$F:$F) -> 0 | E46: =SUM(C46:D46) -> 0 | F46: =IF(AND(B46>0,B46>E46),B46-E46,0) -> 5250 | G46: =IF(AND(B46>0,B46<E46),B46-E46,0) -> 0 | H46: =IF(AND(B46=0,B46<E46),E46-B46,0) -> 0
A47: FRAMING — Subtotal | B47: =SUM(B42:B46) -> 117628.99 | C47: =SUM(C42:C46) -> 0 | D47: =SUM(D42:D46) -> 115633.71 | E47: =SUM(E42:E46) -> 115633.71 | F47: =SUM(F42:F46) -> 20407.205 | G47: =SUM(G42:G46) -> -18411.925 | H47: =SUM(H42:H46) -> 0
A49: WINDOWS
A50: Windows | B50: 32873.736 | D50: =SUMIF(Material!$E:$E,TRIM(A50),Material!$F:$F) -> 25812.63 | E50: =SUM(C50:D50) -> 25812.63 | F50: =IF(AND(B50>0,B50>E50),B50-E50,0) -> 7061.106 | G50: 0 | H50: 0
A51: Blinds | B51: 6300 | D51: =SUMIF(Material!$E:$E,TRIM(A51),Material!$F:$F) -> 0 | E51: =SUM(C51:D51) -> 0 | F51: =IF(AND(B51>0,B51>E51),B51-E51,0) -> 6300 | G51: 0 | H51: 0
A52: WINDOWS — Subtotal | B52: =SUM(B50:B51) -> 39173.736 | C52: =SUM(C50:C51) -> 0 | D52: =SUM(D50:D51) -> 25812.63 | E52: =SUM(E50:E51) -> 25812.63 | F52: =SUM(F50:F51) -> 13361.106 | G52: =SUM(G50:G51) -> 0 | H52: =SUM(H50:H51) -> 0
A54: DOORS
A55: Exterior Doors | B55: 9450 | D55: =SUMIF(Material!$E:$E,TRIM(A55),Material!$F:$F) -> 5894.34 | E55: =SUM(C55:D55) -> 5894.34 | F55: =IF(AND(B55>0,B55>E55),B55-E55,0) -> 3555.66 | G55: =IF(AND(B55>0,B55<E55),B55-E55,0) -> 0 | H55: =IF(AND(B55=0,B55<E55),E55-B55,0) -> 0
A56: Interior Doors | B56: 5250 | D56: =SUMIF(Material!$E:$E,TRIM(A56),Material!$F:$F) -> 265.98 | E56: =SUM(C56:D56) -> 265.98 | F56: =IF(AND(B56>0,B56>E56),B56-E56,0) -> 4984.02 | G56: =IF(AND(B56>0,B56<E56),B56-E56,0) -> 0 | H56: =IF(AND(B56=0,B56<E56),E56-B56,0) -> 0
A57: Garage Doors | B57: 20250.415 | D57: =SUMIF(Material!$E:$E,TRIM(A57),Material!$F:$F) -> 0 | E57: =SUM(C57:D57) -> 0 | F57: =IF(AND(B57>0,B57>E57),B57-E57,0) -> 20250.415 | G57: =IF(AND(B57>0,B57<E57),B57-E57,0) -> 0 | H57: =IF(AND(B57=0,B57<E57),E57-B57,0) -> 0
A58: Door Hardware | B58: 1575 | D58: =SUMIF(Material!$E:$E,TRIM(A58),Material!$F:$F) -> 0 | E58: =SUM(C58:D58) -> 0 | F58: =IF(AND(B58>0,B58>E58),B58-E58,0) -> 1575 | G58: =IF(AND(B58>0,B58<E58),B58-E58,0) -> 0 | H58: =IF(AND(B58=0,B58<E58),E58-B58,0) -> 0
A59: Sliding Door | B59: 16168.509 | D59: =SUMIF(Material!$E:$E,TRIM(A59),Material!$F:$F) -> 15118.53 | E59: =SUM(C59:D59) -> 15118.53 | F59: =IF(AND(B59>0,B59>E59),B59-E59,0) -> 1049.979 | G59: =IF(AND(B59>0,B59<E59),B59-E59,0) -> 0 | H59: =IF(AND(B59=0,B59<E59),E59-B59,0) -> 0
A60: DOORS — Subtotal | B60: =SUM(B55:B59) -> 52693.925 | C60: =SUM(C55:C59) -> 0 | D60: =SUM(D55:D59) -> 21278.85 | E60: =SUM(E55:E59) -> 21278.85 | F60: =SUM(F55:F59) -> 31415.074 | G60: =SUM(G55:G59) -> 0 | H60: =SUM(H55:H59) -> 0
A62: ELECTRICAL
A63: Electrical Rough In & Finish | B63: 70733.25 | D63: =SUMIF(Material!$E:$E,TRIM(A63),Material!$F:$F) -> 55228.71 | E63: =SUM(C63:D63) -> 55228.71 | F63: =IF(AND(B63>0,B63>E63),B63-E63,0) -> 15504.54 | G63: =IF(AND(B63>0,B63<E63),B63-E63,0) -> 0 | H63: =IF(AND(B63=0,B63<E63),E63-B63,0) -> 0
A64: Electrical Rough In & Finish - Change Order | B64: 0 | D64: =SUMIF(Material!$E:$E,TRIM(A64),Material!$F:$F) -> 7333.67 | E64: =SUM(C64:D64) -> 7333.67 | F64: =IF(AND(B64>0,B64>E64),B64-E64,0) -> 0 | G64: =IF(AND(B64>0,B64<E64),B64-E64,0) -> 0 | H64: =IF(AND(B64=0,B64<E64),E64-B64,0) -> 7333.67
A65: Electrical Fixtures | B65: 1050 | D65: =SUMIF(Material!$E:$E,TRIM(A65),Material!$F:$F) -> 0 | E65: =SUM(C65:D65) -> 0 | F65: =IF(AND(B65>0,B65>E65),B65-E65,0) -> 1050 | G65: =IF(AND(B65>0,B65<E65),B65-E65,0) -> 0 | H65: =IF(AND(B65=0,B65<E65),E65-B65,0) -> 0
A66: BC Hydro | B66: 3675 | D66: =SUMIF(Material!$E:$E,TRIM(A66),Material!$F:$F) -> 4887.75 | E66: =SUM(C66:D66) -> 4887.75 | F66: =IF(AND(B66>0,B66>E66),B66-E66,0) -> 0 | G66: =IF(AND(B66>0,B66<E66),B66-E66,0) -> -1212.75 | H66: =IF(AND(B66=0,B66<E66),E66-B66,0) -> 0
A67: ELECTRICAL — Subtotal | B67: =SUM(B63:B66) -> 75458.25 | C67: =SUM(C63:C66) -> 0 | D67: =SUM(D63:D66) -> 67450.13 | E67: =SUM(E63:E66) -> 67450.13 | F67: =SUM(F63:F66) -> 16554.54 | G67: =SUM(G63:G66) -> -1212.75 | H67: =SUM(H63:H66) -> 7333.67
A69: PLUMBING
A70: Plumbing Rough In & Finish | B70: 26250 | D70: =SUMIF(Material!$E:$E,TRIM(A70),Material!$F:$F) -> 29427.32 | E70: =SUM(C70:D70) -> 29427.32 | F70: =IF(AND(B70>0,B70>E70),B70-E70,0) -> 0 | G70: =IF(AND(B70>0,B70<E70),B70-E70,0) -> -3177.32 | H70: =IF(AND(B70=0,B70<E70),E70-B70,0) -> 0
A71: PLUMBING — Subtotal | B71: =SUM(B70:B70) -> 26250 | C71: =SUM(C70:C70) -> 0 | D71: =SUM(D70:D70) -> 29427.32 | E71: =SUM(E70:E70) -> 29427.32 | F71: =SUM(F70:F70) -> 0 | G71: =SUM(G70:G70) -> -3177.32 | H71: =SUM(H70:H70) -> 0
A73: HVAC
A74: Mechanical Rough In & Finish | B74: 56852.25 | D74: =SUMIF(Material!$E:$E,TRIM(A74),Material!$F:$F) -> 29581.13 | E74: =SUM(C74:D74) -> 29581.13 | F74: =IF(AND(B74>0,B74>E74),B74-E74,0) -> 27271.12 | G74: =IF(AND(B74>0,B74<E74),B74-E74,0) -> 0 | H74: =IF(AND(B74=0,B74<E74),E74-B74,0) -> 0
A75: NAVIEN ON DEMAND | B75: 4688.25 | D75: =SUMIF(Material!$E:$E,TRIM(A75),Material!$F:$F) -> 0 | E75: =SUM(C75:D75) -> 0 | F75: =IF(AND(B75>0,B75>E75),B75-E75,0) -> 4688.25 | G75: =IF(AND(B75>0,B75<E75),B75-E75,0) -> 0 | H75: =IF(AND(B75=0,B75<E75),E75-B75,0) -> 0
A76: NAPOLEON GAS FIRE PLACE | B76: 3517.5 | D76: =SUMIF(Material!$E:$E,TRIM(A76),Material!$F:$F) -> 0 | E76: =SUM(C76:D76) -> 0 | F76: =IF(AND(B76>0,B76>E76),B76-E76,0) -> 3517.5 | G76: =IF(AND(B76>0,B76<E76),B76-E76,0) -> 0 | H76: =IF(AND(B76=0,B76<E76),E76-B76,0) -> 0
A77: GAS LINES | B77: 577.5 | D77: =SUMIF(Material!$E:$E,TRIM(A77),Material!$F:$F) -> 0 | E77: =SUM(C77:D77) -> 0 | F77: =IF(AND(B77>0,B77>E77),B77-E77,0) -> 577.5 | G77: =IF(AND(B77>0,B77<E77),B77-E77,0) -> 0 | H77: =IF(AND(B77=0,B77<E77),E77-B77,0) -> 0
A78: Gas/Propane Connection | B78: 577.5 | D78: =SUMIF(Material!$E:$E,TRIM(A78),Material!$F:$F) -> 0 | E78: =SUM(C78:D78) -> 0 | F78: =IF(AND(B78>0,B78>E78),B78-E78,0) -> 577.5 | G78: =IF(AND(B78>0,B78<E78),B78-E78,0) -> 0 | H78: =IF(AND(B78=0,B78<E78),E78-B78,0) -> 0
A79: HVAC — Subtotal | B79: =SUM(B74:B78) -> 66213 | C79: =SUM(C74:C78) -> 0 | D79: =SUM(D74:D78) -> 29581.13 | E79: =SUM(E74:E78) -> 29581.13 | F79: =SUM(F74:F78) -> 36631.87 | G79: =SUM(G74:G78) -> 0 | H79: =SUM(H74:H78) -> 0
A81: ROOFING
A82: Roofing Supply & Install | B82: 34545 | D82: =SUMIF(Material!$E:$E,TRIM(A82),Material!$F:$F) -> 22687.23 | E82: =SUM(C82:D82) -> 22687.23 | F82: =IF(AND(B82>0,B82>E82),B82-E82,0) -> 11857.77 | G82: =IF(AND(B82>0,B82<E82),B82-E82,0) -> 0 | H82: =IF(AND(B82=0,B82<E82),E82-B82,0) -> 0
A83: ROOFING — Subtotal | B83: =SUM(B82:B82) -> 34545 | C83: =SUM(C82:C82) -> 0 | D83: =SUM(D82:D82) -> 22687.23 | E83: =SUM(E82:E82) -> 22687.23 | F83: =SUM(F82:F82) -> 11857.77 | G83: =SUM(G82:G82) -> 0 | H83: =SUM(H82:H82) -> 0
A85: INSULATION & DRYWALL
A86: Insulation | B86: 38921.704 | D86: =SUMIF(Material!$E:$E,TRIM(A86),Material!$F:$F) -> 0 | E86: =SUM(C86:D86) -> 0 | F86: =IF(AND(B86>0,B86>E86),B86-E86,0) -> 38921.704 | G86: =IF(AND(B86>0,B86<E86),B86-E86,0) -> 0 | H86: =IF(AND(B86=0,B86<E86),E86-B86,0) -> 0
A87: Drywall | B87: 50539.891 | D87: =SUMIF(Material!$E:$E,TRIM(A87),Material!$F:$F) -> 89461.6 | E87: =SUM(C87:D87) -> 89461.6 | F87: =IF(AND(B87>0,B87>E87),B87-E87,0) -> 0 | G87: =IF(AND(B87>0,B87<E87),B87-E87,0) -> -38921.709 | H87: =IF(AND(B87=0,B87<E87),E87-B87,0) -> 0
A88: INSULATION & DRYWALL — Subtotal | B88: =SUM(B86:B87) -> 89461.596 | C88: =SUM(C86:C87) -> 0 | D88: =SUM(D86:D87) -> 89461.6 | E88: =SUM(E86:E87) -> 89461.6 | F88: =SUM(F86:F87) -> 38921.704 | G88: =SUM(G86:G87) -> -38921.709 | H88: =SUM(H86:H87) -> 0
A90: EXTERIOR VENEER
A91: Siding Materials | B91: 18640.041 | D91: =SUMIF(Material!$E:$E,TRIM(A91),Material!$F:$F) -> 14171.96 | E91: =SUM(C91:D91) -> 14171.96 | F91: =IF(AND(B91>0,B91>E91),B91-E91,0) -> 4468.081 | G91: =IF(AND(B91>0,B91<E91),B91-E91,0) -> 0 | H91: =IF(AND(B91=0,B91<E91),E91-B91,0) -> 0
A92: Soffit Supply & Install | B92: 15093.75 | D92: =SUMIF(Material!$E:$E,TRIM(A92),Material!$F:$F) -> 0 | E92: =SUM(C92:D92) -> 0 | F92: =IF(AND(B92>0,B92>E92),B92-E92,0) -> 15093.75 | G92: =IF(AND(B92>0,B92<E92),B92-E92,0) -> 0 | H92: =IF(AND(B92=0,B92<E92),E92-B92,0) -> 0
A93: Gutters Supply & Install | B93: 5307.75 | D93: =SUMIF(Material!$E:$E,TRIM(A93),Material!$F:$F) -> 0 | E93: =SUM(C93:D93) -> 0 | F93: =IF(AND(B93>0,B93>E93),B93-E93,0) -> 5307.75 | G93: =IF(AND(B93>0,B93<E93),B93-E93,0) -> 0 | H93: =IF(AND(B93=0,B93<E93),E93-B93,0) -> 0
A94: Trim Labour | B94: 6699 | D94: =SUMIF(Material!$E:$E,TRIM(A94),Material!$F:$F) -> 0 | E94: =SUM(C94:D94) -> 0 | F94: =IF(AND(B94>0,B94>E94),B94-E94,0) -> 6699 | G94: =IF(AND(B94>0,B94<E94),B94-E94,0) -> 0 | H94: =IF(AND(B94=0,B94<E94),E94-B94,0) -> 0
A95: Cedar Soffit | B95: 6023.2095 | D95: =SUMIF(Material!$E:$E,TRIM(A95),Material!$F:$F) -> 0 | E95: =SUM(C95:D95) -> 0 | F95: =IF(AND(B95>0,B95>E95),B95-E95,0) -> 6023.2095 | G95: =IF(AND(B95>0,B95<E95),B95-E95,0) -> 0 | H95: =IF(AND(B95=0,B95<E95),E95-B95,0) -> 0
A96: Stucco | B96: 21000 | D96: =SUMIF(Material!$E:$E,TRIM(A96),Material!$F:$F) -> 0 | E96: =SUM(C96:D96) -> 0 | F96: =IF(AND(B96>0,B96>E96),B96-E96,0) -> 21000 | G96: =IF(AND(B96>0,B96<E96),B96-E96,0) -> 0 | H96: =IF(AND(B96=0,B96<E96),E96-B96,0) -> 0
A97: EXTERIOR VENEER — Subtotal | B97: =SUM(B91:B96) -> 72763.75 | C97: =SUM(C91:C96) -> 0 | D97: =SUM(D91:D96) -> 14171.96 | E97: =SUM(E91:E96) -> 14171.96 | F97: =SUM(F91:F96) -> 58591.791 | G97: =SUM(G91:G96) -> 0 | H97: =SUM(H91:H96) -> 0
A99: MASONRY
A100: Stone Fireplace | B100: 15750 | D100: =SUMIF(Material!$E:$E,TRIM(A100),Material!$F:$F) -> 0 | E100: =SUM(C100:D100) -> 0 | F100: =IF(AND(B100>0,B100>E100),B100-E100,0) -> 15750 | G100: =IF(AND(B100>0,B100<E100),B100-E100,0) -> 0 | H100: =IF(AND(B100=0,B100<E100),E100-B100,0) -> 0
A101: MASONRY — Subtotal | B101: =SUM(B100:B100) -> 15750 | C101: =SUM(C100:C100) -> 0 | D101: =SUM(D100:D100) -> 0 | E101: =SUM(E100:E100) -> 0 | F101: =SUM(F100:F100) -> 15750 | G101: =SUM(G100:G100) -> 0 | H101: =SUM(H100:H100) -> 0
A103: CABINETRY & COUNTERTOPS
A104: Cabinetry Supply & Install | B104: 52500 | D104: =SUMIF(Material!$E:$E,TRIM(A104),Material!$F:$F) -> 0 | E104: =SUM(C104:D104) -> 0 | F104: =IF(AND(B104>0,B104>E104),B104-E104,0) -> 52500 | G104: =IF(AND(B104>0,B104<E104),B104-E104,0) -> 0 | H104: =IF(AND(B104=0,B104<E104),E104-B104,0) -> 0
A105: Countertop Supply & Install | B105: 22974 | D105: =SUMIF(Material!$E:$E,TRIM(A105),Material!$F:$F) -> 0 | E105: =SUM(C105:D105) -> 0 | F105: =IF(AND(B105>0,B105>E105),B105-E105,0) -> 22974 | G105: =IF(AND(B105>0,B105<E105),B105-E105,0) -> 0 | H105: =IF(AND(B105=0,B105<E105),E105-B105,0) -> 0
A106: CABINETRY & COUNTERTOPS — Subtotal | B106: =SUM(B104:B105) -> 75474 | C106: =SUM(C104:C105) -> 0 | D106: =SUM(D104:D105) -> 0 | E106: =SUM(E104:E105) -> 0 | F106: =SUM(F104:F105) -> 75474 | G106: =SUM(G104:G105) -> 0 | H106: =SUM(H104:H105) -> 0
A108: INTERIOR FINISHING
A109: Finishing Carpentry | B109: 4200 | D109: =SUMIF(Material!$E:$E,TRIM(A109),Material!$F:$F) -> 0 | E109: =SUM(C109:D109) -> 0 | F109: =IF(AND(B109>0,B109>E109),B109-E109,0) -> 4200 | G109: =IF(AND(B109>0,B109<E109),B109-E109,0) -> 0 | H109: =IF(AND(B109=0,B109<E109),E109-B109,0) -> 0
A110: Interior Trim Materials | B110: 4488.876 | D110: =SUMIF(Material!$E:$E,TRIM(A110),Material!$F:$F) -> 0 | E110: =SUM(C110:D110) -> 0 | F110: =IF(AND(B110>0,B110>E110),B110-E110,0) -> 4488.876 | G110: =IF(AND(B110>0,B110<E110),B110-E110,0) -> 0 | H110: =IF(AND(B110=0,B110<E110),E110-B110,0) -> 0
A111: Closet Shelving | B111: 5250 | D111: =SUMIF(Material!$E:$E,TRIM(A111),Material!$F:$F) -> 0 | E111: =SUM(C111:D111) -> 0 | F111: =IF(AND(B111>0,B111>E111),B111-E111,0) -> 5250 | G111: =IF(AND(B111>0,B111<E111),B111-E111,0) -> 0 | H111: =IF(AND(B111=0,B111<E111),E111-B111,0) -> 0
A112: Bathroom Hardware | B112: 1050 | D112: =SUMIF(Material!$E:$E,TRIM(A112),Material!$F:$F) -> 0 | E112: =SUM(C112:D112) -> 0 | F112: =IF(AND(B112>0,B112>E112),B112-E112,0) -> 1050 | G112: =IF(AND(B112>0,B112<E112),B112-E112,0) -> 0 | H112: =IF(AND(B112=0,B112<E112),E112-B112,0) -> 0
A113: Shower Glass Doors | B113: 4200 | D113: =SUMIF(Material!$E:$E,TRIM(A113),Material!$F:$F) -> 0 | E113: =SUM(C113:D113) -> 0 | F113: =IF(AND(B113>0,B113>E113),B113-E113,0) -> 4200 | G113: =IF(AND(B113>0,B113<E113),B113-E113,0) -> 0 | H113: =IF(AND(B113=0,B113<E113),E113-B113,0) -> 0
A114: Mirrors | B114: 1050 | D114: =SUMIF(Material!$E:$E,TRIM(A114),Material!$F:$F) -> 0 | E114: =SUM(C114:D114) -> 0 | F114: =IF(AND(B114>0,B114>E114),B114-E114,0) -> 1050 | G114: =IF(AND(B114>0,B114<E114),B114-E114,0) -> 0 | H114: =IF(AND(B114=0,B114<E114),E114-B114,0) -> 0
A115: INTERIOR FINISHING — Subtotal | B115: =SUM(B109:B114) -> 20238.876 | C115: =SUM(C109:C114) -> 0 | D115: =SUM(D109:D114) -> 0 | E115: =SUM(E109:E114) -> 0 | F115: =SUM(F109:F114) -> 20238.876 | G115: =SUM(G109:G114) -> 0 | H115: =SUM(H109:H114) -> 0
A117: WOOD FLOOR COVERINGS
A118: Flooring Material | B118: 12505.5 | D118: =SUMIF(Material!$E:$E,TRIM(A118),Material!$F:$F) -> 0 | E118: =SUM(C118:D118) -> 0 | F118: =IF(AND(B118>0,B118>E118),B118-E118,0) -> 12505.5 | G118: =IF(AND(B118>0,B118<E118),B118-E118,0) -> 0 | H118: =IF(AND(B118=0,B118<E118),E118-B118,0) -> 0
A119: Flooring Install Labour | B119: 12505.5 | D119: =SUMIF(Material!$E:$E,TRIM(A119),Material!$F:$F) -> 0 | E119: =SUM(C119:D119) -> 0 | F119: =IF(AND(B119>0,B119>E119),B119-E119,0) -> 12505.5 | G119: =IF(AND(B119>0,B119<E119),B119-E119,0) -> 0 | H119: =IF(AND(B119=0,B119<E119),E119-B119,0) -> 0
...

Sheet Timesheet
A2: LINE ITEM | B2: Date | C2: Name | D2: Billing Status | E2: Duration
A3: 04 Site Work:Excavation,Backfill,Perimeter &
B4: 46070 | C4: Fielding K Benton | D4: Unbilled | E4: 4
B5: 46070 | C5: Fielding K Benton | D5: Unbilled | E5: 4
B6: 46071 | C6: Fielding K Benton | D6: Unbilled | E6: 4.5
B7: 46071 | C7: Fielding K Benton | D7: Unbilled | E7: 0.67
B8: 46072 | C8: Fielding K Benton | D8: Unbilled | E8: 2.17
B9: 46072 | C9: Fielding K Benton | D9: Unbilled | E9: 0.33
B10: 46073 | C10: Fielding K Benton | D10: Unbilled | E10: 3.83
B11: 46076 | C11: Fielding K Benton | D11: Unbilled | E11: 0.5
B12: 46080 | C12: Fielding K Benton | D12: Unbilled | E12: 5.17
B13: 46080 | C13: Fielding K Benton | D13: Unbilled | E13: 2.83
B14: 46083 | C14: Fielding K Benton | D14: Unbilled | E14: 3.5
B15: 46084 | C15: Fielding K Benton | D15: Unbilled | E15: 0.83
... B25: 46087 | C25: Fielding K Benton | D25: Unbilled | E25: 0.33
A26: Total 04 Site Work:Excavation,Backfill,Perimeter & | E26: 56.24
A27: 05 Foundation:Footings & Foundation Labor
B28: 46076 | C28: Fielding K Benton | D28: Unbilled | E28: 3.83
B29: 46076 | C29: Fielding K Benton | D29: Unbilled | E29: 0.5
B30: 46077 | C30: Fielding K Benton | D30: Unbilled | E30: 4.17
B31: 46078 | C31: Fielding K Benton | D31: Unbilled | E31: 0.17
B32: 46078 | C32: Fielding K Benton | D32: Unbilled | E32: 2.33
B33: 46079 | C33: Alaa Kadah | D33: Unbilled | E33: 3.67
B34: 46083 | C34: Fielding K Benton | D34: Unbilled | E34: 2.67
B35: 46090 | C35: Alaa Kadah | D35: Unbilled | E35: 2.83
B36: 46090 | C36: Alaa Kadah | D36: Unbilled | E36: 4.17
B37: 46090 | C37: Fielding K Benton | D37: Unbilled | E37: 6.17
B38: 46090 | C38: Fielding K Benton | D38: Unbilled | E38: 2.83
B39: 46091 | C39: Alaa Kadah | D39: Unbilled | E39: 4
... B59: 46101 | C59: Fielding K Benton | D59: Unbilled | E59: 3.17
A60: Total 05 Foundation:Footings & Foundation Labor | E60: 90.44
A61: 05 Foundation:Slap Prep Labor
B62: 46198 | C62: Fielding K Benton | D62: Unbilled | E62: 1.25
B63: 46198 | C63: Fielding K Benton | D63: Unbilled | E63: 1.67
B64: 46203 | C64: Fielding K Benton | D64: Unbilled | E64: 0.17
A65: Total 05 Foundation:Slap Prep Labor | E65: 3.09
A66: 06 Framing:Framing Labor
B67: 46104 | C67: Aaron Maskill | D67: Unbilled | E67: 4
B68: 46104 | C68: Aaron Maskill | D68: Unbilled | E68: 3.75
B69: 46104 | C69: Fielding K Benton | D69: Unbilled | E69: 0.75
B70: 46104 | C70: Fielding K Benton | D70: Unbilled | E70: 3.42
B71: 46106 | C71: Aaron Maskill | D71: Unbilled | E71: 4.25
B72: 46106 | C72: Aaron Maskill | D72: Unbilled | E72: 0
B73: 46106 | C73: Aaron Maskill | D73: Unbilled | E73: 5.58
B74: 46106 | C74: Fielding K Benton | D74: Unbilled | E74: 2.58
B75: 46106 | C75: Fielding K Benton | D75: Unbilled | E75: 3.25
B76: 46107 | C76: Aaron Maskill | D76: Unbilled | E76: 4.25
B77: 46107 | C77: Aaron Maskill | D77: Unbilled | E77: 3.08
B78: 46107 | C78: Fielding K Benton | D78: Unbilled | E78: 5.33
... B337: 46203 | C337: Fielding K Benton | D337: Unbilled | E337: 0.92
A338: Total 06 Framing:Framing Labor | E338: 974.53
A339: 06 Framing:Timber Framing Labour Cost
B340: 46171 | C340: James McMann | D340: Unbilled | E340: 1.92
B341: 46171 | C341: James McMann | D341: Unbilled | E341: 1.08
A342: Total 06 Framing:Timber Framing Labour Cost | E342: 3
A343: 14 Exterior Veneer:Siding Labor
B344: 46185 | C344: Alexander D Gazzola | D344: Unbilled | E344: 5.08
B345: 46193 | C345: Alexander D Gazzola | D345: Unbilled | E345: 7.08
B346: 46193 | C346: Alexander D Gazzola | D346: Unbilled | E346: 2.92
B347: 46193 | C347: Alexander D Gazzola | D347: Unbilled | E347: 1.42
A348: Total 14 Exterior Veneer:Siding Labor | E348: 16.5
A349: 21 Exterior Areas & Finishes:Landscaping
B350: 46114 | C350: Alaa Kadah | D350: Unbilled | E350: 3.17
B351: 46127 | C351: Alaa Kadah | D351: Unbilled | E351: 0
A352: Total 21 Exterior Areas & Finishes:Landscaping | E352: 3.17
A353: 22 Construction Clean Up:Clean Labour
B354: 46104 | C354: Fielding K Benton | D354: Unbilled | E354: 0
B355: 46182 | C355: Alaa Kadah | D355: Unbilled | E355: 4.5
B356: 46182 | C356: Alaa Kadah | D356: Unbilled | E356: 2.75
B357: 46203 | C357: Fielding K Benton | D357: Unbilled | E357: 1.33
A358: Total 22 Construction Clean Up:Clean Labour | E358: 8.58
A359: 24 Supervision:Project Managment
B360: 46078 | C360: James McMann | D360: Unbilled | E360: 1.83
B361: 46169 | C361: James McMann | D361: Unbilled | E361: 2.83
A362: Total 24 Supervision:Project Managment | E362: 4.66
E363: 1160.21
A364: Total Timesheet | E364: =ROUND(E27+E61+E66+E339+E343+E349+E353+E359+E363,5) -> 1160.21

Sheet Material
B1: Type | C1: Date | D1: Num | E1: Memo | F1: Amount
A2: 1047335 B.C. LTD (dba Complete Damp Proof
B3: Bill | C3: 46086 | D3: 11452 | E3: Damproofing | F3: 3379.95
A4: Total 1047335 B.C. LTD (dba Complete Damp Proof | F4: =ROUND(SUM(F2:F3),5) -> 3379.95
A5: ABC Supply and Co
B6: Credit Card Charge | C6: 46176 | E6: Roofing Supply & Install | F6: 2295.86
B7: Credit Card Credit | C7: 46183 | E7: Roofing Supply & Install | F7: -492.1
B8: Credit Card Charge | C8: 46203 | D8: 257305 | E8: Roofing Supply & Install | F8: 871.84
B9: Bill | C9: 46206 | D9: 319570 | E9: Roofing Supply & Install | F9: 4113.69
B10: Credit Card Credit | C10: 46206 | E10: Roofing Supply & Install | F10: -336.46
A11: Total ABC Supply and Co | F11: =ROUND(SUM(F5:F10),5) -> 6452.83
A12: Andrew Sheret Ltd
B13: Bill | C13: 46080 | D13: 03-084405 | E13: Backfill, Perimeter & Drain Material | F13: 411.09
B14: Bill | C14: 46083 | D14: 03-084596 | E14: Backfill, Perimeter & Drain Material | F14: 1162.28
B15: Bill | C15: 46088 | D15: 03-085259 | E15: Backfill, Perimeter & Drain Material | F15: 408.36
B16: Bill | C16: 46090 | D16: 03-085292 | E16: Backfill, Perimeter & Drain Material | F16: 227.04
B17: Bill | C17: 46091 | D17: 03-085458 | E17: Backfill, Perimeter & Drain Material | F17: 627.47
B18: Credit | C18: 46091 | D18: 03-085563 | E18: Backfill, Perimeter & Drain Material | F18: -255.26
B19: Bill | C19: 46093 | D19: 03-085864 | E19: Backfill, Perimeter & Drain Material | F19: 533.88
B20: Bill | C20: 46139 | D20: 03-090686 | E20: Backfill, Perimeter & Drain Material | F20: 797.73
B21: Bill | C21: 46154 | D21: 03-092447 | E21: Backfill, Perimeter & Drain Material | F21: 510.81
B22: Bill | C22: 46183 | D22: 03-095733 | E22: Backfill, Perimeter & Drain Material | F22: 7.66
B23: Bill | C23: 46185 | D23: 03-095751 | E23: Backfill, Perimeter & Drain Material | F23: 159.4
B24: Bill | C24: 46186 | D24: 03-096046 | E24: Backfill, Perimeter & Drain Material | F24: 58.29
... B30: Credit | C30: 46210 | D30: 03-096011 | E30: Backfill, Perimeter & Drain Material | F30: -6.07
A31: Total Andrew Sheret Ltd | F31: =ROUND(SUM(F12:F30),5) -> 12821.55
A32: BC Housing Licensing & Consumer Services
B33: Bill | C33: 46000 | D33: 875433 | E33: BC Housing Registration Fee | F33: 40
A34: Total BC Housing Licensing & Consumer Services | F34: =ROUND(SUM(F32:F33),5) -> 40
A35: BC Hydro
B36: Cheque | C36: 46203 | D36: Direct | E36: BC Hydro | F36: 4887.75
A37: Total BC Hydro | F37: =ROUND(SUM(F35:F36),5) -> 4887.75
A38: Bryan's Mechanical Ltd.
B39: Bill | C39: 46197 | D39: 696-D396-1 | E39: Mechanical Rough In & Finish | F39: 29581.13
A40: Total Bryan's Mechanical Ltd. | F40: =ROUND(SUM(F38:F39),5) -> 29581.13
A41: Chevron
B42: Credit Card Charge | C42: 46184 | E42: Framing Materials Cost | F42: 36.89
B43: Credit Card Charge | C43: 46190 | E43: Framing Materials Cost | F43: 47.34
B44: Credit Card Charge | C44: 46196 | E44: Framing Materials Cost | F44: 250
B45: Credit Card Charge | C45: 46216 | E45: Framing Materials Cost | F45: 250
A46: Total Chevron | F46: =ROUND(SUM(F41:F45),5) -> 584.23
A47: City of Nanaimo
B48: Bill | C48: 46035 | D48: BP131412 | E48: Building Permit Fees | F48: 739.5
B49: Credit Card Charge | C49: 46072 | E49: Building Permit Fees | F49: 7400.35
B50: Credit Card Charge | C50: 46230 | D50: BP131412 | E50: Building Permit Fees | F50: 76.5
A51: Total City of Nanaimo | F51: =ROUND(SUM(F47:F50),5) -> 8216.35
A52: Coast To Coast Equipment Rentals LTD
B53: Bill | C53: 46106 | D53: R1692-1 | E53: Specialty Tool & Equipment Rental | F53: 1675.88
A54: Total Coast To Coast Equipment Rentals LTD | F54: =ROUND(SUM(F52:F53),5) -> 1675.88
A55: Coastline Plumbing Ltd
B56: Bill | C56: 46094 | D56: 3142 | E56: Plumbing Rough In & Finish | F56: 1422.77
B57: Bill | C57: 46203 | D57: 3266 | E57: Plumbing Rough In & Finish | F57: 28004.55
A58: Total Coastline Plumbing Ltd | F58: =ROUND(SUM(F55:F57),5) -> 29427.32
A59: DBL Disposal Services Ltd
B60: Bill | C60: 46097 | D60: 275197 | E60: Portable Toilet | F60: 78.75
B61: Bill | C61: 46112 | D61: 275170 | E61: Portable Toilet | F61: 130.4
B62: Bill | C62: 46142 | D62: 284099 | E62: Portable Toilet | F62: 183.75
B63: Bill | C63: 46173 | D63: 295928 | E63: Portable Toilet | F63: 183.75
B64: Bill | C64: 46184 | D64: 312822 | E64: Disposal & Dump Fees | F64: 1664.96
B65: Bill | C65: 46203 | D65: 307837 | E65: Portable Toilet | F65: 91.88
A66: Total DBL Disposal Services Ltd | F66: =ROUND(SUM(F59:F65),5) -> 2333.49
A67: Ecolibrium Energy Solutions Inc.
B68: Bill | C68: 45954 | D68: 2354 | E68: Energy Advisor | F68: 918.75
A69: Total Ecolibrium Energy Solutions Inc. | F69: =ROUND(SUM(F67:F68),5) -> 918.75
A70: Fielding K Benton.
B71: Cheque | C71: 46073 | D71: 372 | E71: Backfill, Perimeter & Drain Material | F71: 130.28
A72: Total Fielding K Benton. | F72: =ROUND(SUM(F70:F71),5) -> 130.28
A73: Gregg Distributors (Nanaimo) Ltd.
B74: Credit Card Charge | C74: 46190 | E74: Framing Materials Cost | F74: 132.38
A75: Total Gregg Distributors (Nanaimo) Ltd. | F75: =ROUND(SUM(F73:F74),5) -> 132.38
A76: Harleen Parmar
B77: Cheque | C77: 46169 | D77: 429 | E77: Roof Trusses | F77: 20000
B78: Bill | C78: 46173 | E78: Roof Trusses | F78: 23603.7
B79: Bill | C79: 46173 | E79: Floor System | F79: 12383
A80: Total Harleen Parmar | F80: =ROUND(SUM(F76:F79),5) -> 55986.7
A81: Heidelberg Materials Canada Limited
B82: Bill | C82: 46073 | D82: 3183511 | E82: Foundation & Footings concrete | F82: 9798.42
B83: Bill | C83: 46084 | D83: 3184417 | E83: Foundation & Footings concrete | F83: 13751.36
B84: Bill | C84: 46094 | D84: 3185376 | E84: Concrete Skim Coat Materials | F84: 5354.94
B85: Bill | C85: 46192 | D85: 3193797 | E85: Garage Concrete Slab | F85: 4074.01
A86: Total Heidelberg Materials Canada Limited | F86: =ROUND(SUM(F81:F85),5) -> 32978.73
A87: Immersive Design Inc
B88: Bill | C88: 45961 | D88: 25103103 | E88: Plan Desgin | F88: 9246.3
A89: Total Immersive Design Inc | F89: =ROUND(SUM(F87:F88),5) -> 9246.3
A90: Island Aggregates Ltd
B91: Credit Card Charge | C91: 46083 | E91: Backfill, Perimeter & Drain Material | F91: 292.89
B92: Credit Card Charge | C92: 46083 | E92: Backfill, Perimeter & Drain Material | F92: 256.66
B93: Credit Card Charge | C93: 46084 | E93: Backfill, Perimeter & Drain Material | F93: 287.68
B94: Credit Card Charge | C94: 46084 | E94: Backfill, Perimeter & Drain Material | F94: 284.2
B95: Credit Card Charge | C95: 46087 | E95: Backfill, Perimeter & Drain Material | F95: 282.04
B96: Credit Card Charge | C96: 46087 | E96: Backfill, Perimeter & Drain Material | F96: 288.55
B97: Credit Card Charge | C97: 46087 | E97: Backfill, Perimeter & Drain Material | F97: 294.2
B98: Credit Card Charge | C98: 46087 | E98: Backfill, Perimeter & Drain Material | F98: 574.93
B99: Credit Card Charge | C99: 46090 | E99: Backfill, Perimeter & Drain Material | F99: 295.94
B100: Credit Card Charge | C100: 46090 | E100: Backfill, Perimeter & Drain Material | F100: 296.37
B101: Credit Card Charge | C101: 46091 | E101: Backfill, Perimeter & Drain Material | F101: 290.28
B102: Credit Card Charge | C102: 46091 | E102: Backfill, Perimeter & Drain Material | F102: 296.37
... B118: Credit Card Charge | C118: 46094 | E118: Backfill, Perimeter & Drain Material | F118: 486.07
A119: Total Island Aggregates Ltd | F119: =ROUND(SUM(F90:F118),5) -> 9497.61
A120: Island Concrete Pumping Ltd
...
